documentcloud/__init__.py
documentcloud/addon.py
documentcloud/annotations.py
documentcloud/base.py
documentcloud/client.py
documentcloud/constants.py
documentcloud/documents.py
documentcloud/exceptions.py
documentcloud/organizations.py
documentcloud/projects.py
documentcloud/sections.py
documentcloud/toolbox.py
documentcloud/users.py
python_documentcloud2-3.0.0.dist-info/LICENSE
python_documentcloud2-3.0.0.dist-info/METADATA
python_documentcloud2-3.0.0.dist-info/WHEEL
python_documentcloud2-3.0.0.dist-info/top_level.txt
python_documentcloud2-3.0.0.dist-info/RECORD
