Metadata-Version: 2.1
Name: python-documentcloud2
Version: 3.0.0
Summary: A simple Python wrapper for the DocumentCloud API
Home-page: https://github.com/muckrock/python-documentcloud
Author: Mitchell Kotler
Author-email: mitch@muckrock.com
License: MIT
Platform: UNKNOWN
Requires-Dist: python-documentcloud
